{
    "format": "attributes",
    "animation": [
        {
            "name": "Root",
            "time": [0.0, 1.1667, 2.3333],
            "transform": [
                {
                    "loc": [0.0, 0.0, 0.0],
                    "rot": [1.0, 0.0, 0.0, 0.0],
                    "sca": [1.0, 1.0, 1.0]
                },
                {
                    "loc": [0.0, -0.01845, 0.0],
                    "rot": [1.0, 0.0, 0.0, 0.0],
                    "sca": [1.0, 1.0, 1.0]
                },
                {
                    "loc": [0.0, 0.0, 0.0],
                    "rot": [1.0, 0.0, 0.0, 0.0],
                    "sca": [1.0, 1.0, 1.0]
                }
            ]
        },
        {
            "name": "Torso",
            "time": [0.0, 2.3333],
            "transform": [
                {
                    "loc": [0.0, 0.0, 0.0],
                    "rot": [1.0, 0.0, 0.0, 0.0],
                    "sca": [1.0, 1.0, 1.0]
                },
                {
                    "loc": [0.0, 0.0, 0.0],
                    "rot": [1.0, 0.0, 0.0, 0.0],
                    "sca": [1.0, 1.0, 1.0]
                }
            ]
        },
        {
            "name": "Chest",
            "time": [0.0, 2.3333],
            "transform": [
                {
                    "loc": [0.0, 0.0, 0.0],
                    "rot": [1.0, 0.0, 0.0, 0.0],
                    "sca": [1.0, 1.0, 1.0]
                },
                {
                    "loc": [0.0, 0.0, 0.0],
                    "rot": [1.0, 0.0, 0.0, 0.0],
                    "sca": [1.0, 1.0, 1.0]
                }
            ]
        },
        {
            "name": "Shoulder_R",
            "time": [0.0, 2.3333],
            "transform": [
                {
                    "loc": [0.0, 0.0, 0.0],
                    "rot": [1.0, -0.0, 0.0, -0.0],
                    "sca": [1.0, 1.0, 1.0]
                },
                {
                    "loc": [0.0, 0.0, 0.0],
                    "rot": [1.0, -0.0, 0.0, -0.0],
                    "sca": [1.0, 1.0, 1.0]
                }
            ]
        },
        {
            "name": "Arm_R",
            "time": [0.0, 1.1667, 2.3333],
            "transform": [
                {
                    "loc": [0.107987, 0.001543, 0.276041],
                    "rot": [0.577123, 0.421913, -0.511566, -0.476675],
                    "sca": [1.0, 1.0, 1.0]
                },
                {
                    "loc": [0.107987, 0.001401, 0.276087],
                    "rot": [0.572011, 0.428818, -0.493042, -0.49581],
                    "sca": [1.0, 1.0, 1.0]
                },
                {
                    "loc": [0.107987, 0.001543, 0.276041],
                    "rot": [0.577123, 0.421913, -0.511566, -0.476675],
                    "sca": [1.0, 1.0, 1.0]
                }
            ]
        },
        {
            "name": "Hand_R",
            "time": [0.0, 2.3333],
            "transform": [
                {
                    "loc": [0.0, -0.0, 0.0],
                    "rot": [0.997716, 0.067553, 0.0, 0.0],
                    "sca": [1.0, 1.0, 1.0]
                },
                {
                    "loc": [0.0, -0.0, 0.0],
                    "rot": [0.997716, 0.067553, 0.0, 0.0],
                    "sca": [1.0, 1.0, 1.0]
                }
            ]
        },
        {
            "name": "Tool_R",
            "time": [0.0, 2.3333],
            "transform": [
                {
                    "loc": [0.0, 0.0, 0.0],
                    "rot": [1.0, 0.0, -0.0, 0.0],
                    "sca": [1.0, 1.0, 1.000015]
                },
                {
                    "loc": [0.0, 0.0, 0.0],
                    "rot": [1.0, 0.0, -0.0, 0.0],
                    "sca": [1.0, 1.0, 1.000015]
                }
            ]
        },
        {
            "name": "Elbow_R",
            "time": [0.0, 2.3333],
            "transform": [
                {
                    "loc": [4.9e-05, -0.000652, -0.070249],
                    "rot": [1.0, 0.0, 0.0, -0.0],
                    "sca": [1.0, 1.0, 1.0]
                },
                {
                    "loc": [4.9e-05, -0.000652, -0.070249],
                    "rot": [1.0, 0.0, 0.0, -0.0],
                    "sca": [1.0, 1.0, 1.0]
                }
            ]
        },
        {
            "name": "Shoulder_L",
            "time": [0.0, 2.3333],
            "transform": [
                {
                    "loc": [-0.0, 0.0, -0.0],
                    "rot": [1.0, -0.0, -0.0, 0.0],
                    "sca": [1.0, 1.0, 1.0]
                },
                {
                    "loc": [-0.0, 0.0, -0.0],
                    "rot": [1.0, -0.0, -0.0, 0.0],
                    "sca": [1.0, 1.0, 1.0]
                }
            ]
        },
        {
            "name": "Arm_L",
            "time": [0.0, 1.1667, 2.3333],
            "transform": [
                {
                    "loc": [-0.096828, -0.000429, 0.270396],
                    "rot": [0.590448, 0.399755, 0.498645, 0.492869],
                    "sca": [1.0, 1.0, 1.0]
                },
                {
                    "loc": [-0.096828, -0.000287, 0.270351],
                    "rot": [0.583446, 0.409907, 0.482207, 0.508963],
                    "sca": [1.0, 1.0, 1.0]
                },
                {
                    "loc": [-0.096828, -0.000429, 0.270396],
                    "rot": [0.590448, 0.399755, 0.498645, 0.492869],
                    "sca": [1.0, 1.0, 1.0]
                }
            ]
        },
        {
            "name": "Hand_L",
            "time": [0.0, 2.3333],
            "transform": [
                {
                    "loc": [0.0, -0.0, -0.0],
                    "rot": [0.995955, 0.089859, 0.0, 0.0],
                    "sca": [1.0, 1.0, 1.0]
                },
                {
                    "loc": [0.0, -0.0, -0.0],
                    "rot": [0.995955, 0.089859, 0.0, 0.0],
                    "sca": [1.0, 1.0, 1.0]
                }
            ]
        },
        {
            "name": "Tool_L",
            "time": [0.0, 2.3333],
            "transform": [
                {
                    "loc": [-0.0, 0.0, -0.0],
                    "rot": [1.0, -0.0, 0.0, 0.0],
                    "sca": [1.0, 1.0, 1.000019]
                },
                {
                    "loc": [-0.0, 0.0, -0.0],
                    "rot": [1.0, -0.0, 0.0, 0.0],
                    "sca": [1.0, 1.0, 1.000019]
                }
            ]
        },
        {
            "name": "Elbow_L",
            "time": [0.0, 2.3333],
            "transform": [
                {
                    "loc": [0.000104, -7.1e-05, -0.067344],
                    "rot": [1.0, 0.0, -0.0, 0.0],
                    "sca": [1.0, 1.0, 1.0]
                },
                {
                    "loc": [0.000104, -7.1e-05, -0.067344],
                    "rot": [1.0, 0.0, -0.0, 0.0],
                    "sca": [1.0, 1.0, 1.0]
                }
            ]
        }
    ]
}